{
  "id": "home_about_us",
  "type": "SharedSlice",
  "name": "HomeAboutUs",
  "description": "HomeAboutUs",
  "variations": [
    {
      "id": "default",
      "name": "Default",
      "docURL": "...",
      "version": "sktwi1xtmkfgx8626",
      "description": "HomeAboutUs",
      "primary": {
        "text": {
          "type": "StructuredText",
          "config": {
            "label": "Text",
            "placeholder": "",
            "allowTargetBlank": true,
            "multi": "paragraph,heading1,heading3,strong,em,rtl,heading2"
          }
        },
        "image": {
          "type": "Image",
          "config": {
            "label": "Image",
            "constraint": {},
            "thumbnails": []
          }
        },
        "background_image": {
          "type": "Image",
          "config": {
            "label": "Background Image",
            "constraint": {},
            "thumbnails": []
          }
        }
      },
      "items": {},
      "imageUrl": "https://images.prismic.io/slice-machine/621a5ec4-0387-4bc5-9860-2dd46cbc07cd_default_ss.png?auto=compress,format"
    }
  ]
}